py_nasa_api/__init__.py
py_nasa_api/api/__init__.py
py_nasa_api/api/http/__init__.py
py_nasa_api/api/http/http_client.py
py_nasa_api/api/http/route.py
py_nasa_api/client/__init__.py
py_nasa_api/client/client.py
py_nasa_api/client/const.py
py_nasa_api/client/utils/__init__.py
py_nasa_api/client/utils/misc.py
py_nasa_api/client/utils/warning.py
py_nasa_api/models/__init__.py
py_nasa_api/models/response.py
py_nasa_api-0.1.1.dist-info/LICENSE
py_nasa_api-0.1.1.dist-info/METADATA
py_nasa_api-0.1.1.dist-info/WHEEL
py_nasa_api-0.1.1.dist-info/RECORD
