Metadata-Version: 2.3
Name: py-nasa-api
Version: 0.1.1
Summary: NASA API wrapper written in Python
Author: Keenan Noack
Author-email: AlbertUnruh@pm.me
Requires-Python: >=3.12
Classifier: Programming Language :: Python :: 3
Classifier: Programming Language :: Python :: 3.12
Classifier: Programming Language :: Python :: 3.13
Requires-Dist: aiohttp (>=3.11.16,<4.0.0)
Requires-Dist: orjson (>=3.10.16,<4.0.0)
Project-URL: Homepage, https://github.com/AlbertUnruh/py-nasa-api
Project-URL: issues, https://github.com/AlbertUnruh/py-nasa-api/issues
Project-URL: soucecode, https://github.com/AlbertUnruh/py-nasa-api
